odoo/addons/sale_variant_configurator/README.rst
odoo/addons/sale_variant_configurator/__init__.py
odoo/addons/sale_variant_configurator/__manifest__.py
odoo/addons/sale_variant_configurator/hooks.py
odoo/addons/sale_variant_configurator/i18n/ca.po
odoo/addons/sale_variant_configurator/i18n/de.po
odoo/addons/sale_variant_configurator/i18n/es.po
odoo/addons/sale_variant_configurator/i18n/es_AR.po
odoo/addons/sale_variant_configurator/i18n/es_CR.po
odoo/addons/sale_variant_configurator/i18n/es_MX.po
odoo/addons/sale_variant_configurator/i18n/es_VE.po
odoo/addons/sale_variant_configurator/i18n/fi.po
odoo/addons/sale_variant_configurator/i18n/fr.po
odoo/addons/sale_variant_configurator/i18n/fr_CH.po
odoo/addons/sale_variant_configurator/i18n/gl.po
odoo/addons/sale_variant_configurator/i18n/hr.po
odoo/addons/sale_variant_configurator/i18n/hr_HR.po
odoo/addons/sale_variant_configurator/i18n/hu.po
odoo/addons/sale_variant_configurator/i18n/it.po
odoo/addons/sale_variant_configurator/i18n/mk.po
odoo/addons/sale_variant_configurator/i18n/mn.po
odoo/addons/sale_variant_configurator/i18n/nl.po
odoo/addons/sale_variant_configurator/i18n/nl_NL.po
odoo/addons/sale_variant_configurator/i18n/pl.po
odoo/addons/sale_variant_configurator/i18n/pt.po
odoo/addons/sale_variant_configurator/i18n/pt_BR.po
odoo/addons/sale_variant_configurator/i18n/pt_PT.po
odoo/addons/sale_variant_configurator/i18n/ro.po
odoo/addons/sale_variant_configurator/i18n/ru.po
odoo/addons/sale_variant_configurator/i18n/sale_variant_configurator.pot
odoo/addons/sale_variant_configurator/i18n/sl.po
odoo/addons/sale_variant_configurator/i18n/sv.po
odoo/addons/sale_variant_configurator/i18n/tr.po
odoo/addons/sale_variant_configurator/i18n/tr_TR.po
odoo/addons/sale_variant_configurator/i18n/vi_VN.po
odoo/addons/sale_variant_configurator/i18n/zh_CN.po
odoo/addons/sale_variant_configurator/models/__init__.py
odoo/addons/sale_variant_configurator/models/sale_order.py
odoo11_addon_sale_variant_configurator-11.0.1.2.0.dist-info/METADATA
odoo11_addon_sale_variant_configurator-11.0.1.2.0.dist-info/RECORD
odoo11_addon_sale_variant_configurator-11.0.1.2.0.dist-info/WHEEL
odoo11_addon_sale_variant_configurator-11.0.1.2.0.dist-info/top_level.txt
